lightcast_client/OAuthClient.py
lightcast_client/__init__.py
lightcast_client/client.py
lightcast_client/global_dataset.py
lightcast_client/taxonomy.py
lightcast_client/uk_dataset.py
lightcast_insight/__init__.py
lightcast_insight/occupation_insight.py
lightcast_insight/taxonomy_insight.py
lightcast_smart_dataset-0.1.33.data/scripts/lightcast-smart-dataset
tests/__init__.py
tests/test_client.py
tests/test_global_dataset.py
tests/test_oauth.py
tests/test_taxonony.py
tests/test_uk_dataset.py
lightcast_smart_dataset-0.1.33.dist-info/METADATA
lightcast_smart_dataset-0.1.33.dist-info/WHEEL
lightcast_smart_dataset-0.1.33.dist-info/top_level.txt
lightcast_smart_dataset-0.1.33.dist-info/RECORD
