Metadata-Version: 2.1
Name: lightcast-smart-dataset
Version: 0.1.33
Summary: Utility use the Lightcast Global Smart Dataset
Home-page: https://github.com/Lightcast-Global-Innovation/global-smart-dataset
Author: Global Data Science Team - Lightcast
Author-email: globaldatascience@lightcast.io
Classifier: Programming Language :: Python :: 2.7
Classifier: Programming Language :: Python :: 3.7
Classifier: License :: OSI Approved :: MIT License
Classifier: Operating System :: OS Independent
Requires-Dist: requests
Requires-Dist: xlsxwriter
Requires-Dist: pandas
Requires-Dist: docopt
